app/__init__.py
app/calc.py
app/cmd.py
my_ip_calulator-1.0.9.dist-info/LICENSE
my_ip_calulator-1.0.9.dist-info/METADATA
my_ip_calulator-1.0.9.dist-info/WHEEL
my_ip_calulator-1.0.9.dist-info/entry_points.txt
my_ip_calulator-1.0.9.dist-info/RECORD
