Metadata-Version: 2.1
Name: my-ip-calulator
Version: 1.0.9
Summary: This is an IPv4 and IPv6 calculator. It can validate IP address, convert then and also do net and subnet calculations.
Home-page: https://brunobotelhobr.github.io/My-IP-Calculator
License: MIT
Keywords: ip,calculator,ipv4,ipv6,net,subnet,cidr,mask,address,convert,validate
Author: Bruno Botelho
Author-email: bruno.botelho.br@gmail.com
Maintainer: Bruno Botelho
Maintainer-email: bruno.botelho.br@gmail.com
Requires-Python: >=3.10,<4.0
Classifier: License :: OSI Approved :: MIT License
Classifier: Programming Language :: Python :: 3
Classifier: Programming Language :: Python :: 3.10
Classifier: Programming Language :: Python :: 3.11
Classifier: Programming Language :: Python :: 3.12
Requires-Dist: rich (>=13.3.5,<14.0.0)
Requires-Dist: typer[all] (>=0.9.0,<0.10.0)
Project-URL: Repository, https://github.com/brunobotelhobr/My-IP-Calculator
